argument_names-0.1.0a2.dist-info/METADATA
argument_names-0.1.0a2.dist-info/WHEEL
argument_names-0.1.0a2.dist-info/entry_points.txt
argument_names-0.1.0a2.dist-info/licenses/LICENSE
argument_names/__init__.py
argument_names/__main__.py
argument_names-0.1.0a2.dist-info/RECORD
