Metadata-Version: 2.1
Name: argument-names
Version: 0.1.0a2
Summary: This decorator dynamically maps argument names from a function's call to a specified function.
Keywords: decorator,argument names,Python,type checking
Author-Email: Santiago Papiernik <spapiernik12@gmail.com>
License: MIT License
Classifier: License :: OSI Approved :: MIT License
Classifier: Intended Audience :: Developers
Classifier: Programming Language :: Python :: 3
Classifier: Programming Language :: Python :: 3 :: Only
Classifier: Programming Language :: Python :: 3.8
Classifier: Programming Language :: Python :: 3.9
Classifier: Programming Language :: Python :: 3.10
Classifier: Programming Language :: Python :: 3.11
Classifier: Programming Language :: Python :: 3.12
Classifier: Programming Language :: Python :: 3.13
Classifier: Typing :: Typed
Project-URL: Repository, https://github.com/Cxx-mlr/identifiers
Requires-Python: >=3.8
Requires-Dist: packaging>=24.1
Requires-Dist: typing-extensions>=4.12.2
